Workbook

Sheet Assumptions
A1: Assumptions | B1: Value
A3: Revenue 2024 | B3: 1000
A4: Revenue growth | B4: 0.05
A5: EBITDA margin | B5: 0.22
A6: Tax rate | B6: 0.25
A7: D&A % of revenue | B7: 0.03
A8: Capex % of revenue | B8: 0.04
A9: NWC % of revenue | B9: 0.1
A10: WACC | B10: 0.09
A11: Terminal growth | B11: 0.025
A12: Net debt | B12: 350
A13: Shares outstanding | B13: 100
A14: Valuation date | B14: 45657

Sheet DCF
A1: DCF ($m)
A3: Year | B3: 2024 | C3: =B3+1 -> 2025 | D3: =C3+1 -> 2026 | E3: =D3+1 -> 2027 | F3: =E3+1 -> 2028 | G3: =F3+1 -> 2029
A4: Revenue | B4: =Assumptions!B3 -> 1000 | C4: =B4*(1+Growth) -> 1050 | D4: =C4*(1+Growth) -> 1102.5 | E4: =D4*(1+Growth) -> 1157.625 | F4: =E4*(1+Growth) -> 1215.5062 | G4: =F4*(1+Growth) -> 1276.2816
A5: EBITDA | C5: =C4*Margin -> 231 | D5: =D4*Margin -> 242.55 | E5: =E4*Margin -> 254.6775 | F5: =F4*Margin -> 267.41138 | G5: =G4*Margin -> 280.78194
A6: D&A | C6: =C4*Assumptions!$B$7 -> 31.5 | D6: =D4*Assumptions!$B$7 -> 33.075 | E6: =E4*Assumptions!$B$7 -> 34.72875 | F6: =F4*Assumptions!$B$7 -> 36.465187 | G6: =G4*Assumptions!$B$7 -> 38.288447
A7: EBIT | C7: =C5-C6 -> 199.5 | D7: =D5-D6 -> 209.475 | E7: =E5-E6 -> 219.94875 | F7: =F5-F6 -> 230.94619 | G7: =G5-G6 -> 242.4935
A8: Taxes | C8: =MAX(0,C7*TaxRate) -> 49.875 | D8: =MAX(0,D7*TaxRate) -> 52.36875 | E8: =MAX(0,E7*TaxRate) -> 54.987187 | F8: =MAX(0,F7*TaxRate) -> 57.736547 | G8: =MAX(0,G7*TaxRate) -> 60.623374
A9: NOPAT | C9: =C7-C8 -> 149.625 | D9: =D7-D8 -> 157.10625 | E9: =E7-E8 -> 164.96156 | F9: =F7-F8 -> 173.20964 | G9: =G7-G8 -> 181.87012
A10: Capex | C10: =C4*Assumptions!$B$8 -> 42 | D10: =D4*Assumptions!$B$8 -> 44.1 | E10: =E4*Assumptions!$B$8 -> 46.305 | F10: =F4*Assumptions!$B$8 -> 48.62025 | G10: =G4*Assumptions!$B$8 -> 51.051262
A11: Change in NWC | C11: =(C4-B4)*Assumptions!$B$9 -> 5 | D11: =(D4-C4)*Assumptions!$B$9 -> 5.25 | E11: =(E4-D4)*Assumptions!$B$9 -> 5.5125 | F11: =(F4-E4)*Assumptions!$B$9 -> 5.788125 | G11: =(G4-F4)*Assumptions!$B$9 -> 6.0775313
A12: Free cash flow | C12: =C9+C6-C10-C11 -> 134.125 | D12: =D9+D6-D10-D11 -> 140.83125 | E12: =E9+E6-E10-E11 -> 147.87281 | F12: =F9+F6-F10-F11 -> 155.26645 | G12: =G9+G6-G10-G11 -> 163.02978
A13: Discount factor | C13: =1/(1+WACC)^(C3-$B$3) -> 0.91743119 | D13: =1/(1+WACC)^(D3-$B$3) -> 0.84167999 | E13: =1/(1+WACC)^(E3-$B$3) -> 0.77218348 | F13: =1/(1+WACC)^(F3-$B$3) -> 0.70842521 | G13: =1/(1+WACC)^(G3-$B$3) -> 0.64993139
A14: PV of free cash flow | C14: =C12*C13 -> 123.05046 | D14: =D12*D13 -> 118.53485 | E14: =E12*E13 -> 114.18494 | F14: =F12*F13 -> 109.99467 | G14: =G12*G13 -> 105.95817
A16: Sum of PV | B16: =SUM(C14:G14) -> 571.72309
A17: Terminal value | B17: =G12*(1+Assumptions!B11)/(WACC-Assumptions!B11) -> 2570.8542
A18: PV of terminal value | B18: =B17*G13 -> 1670.8788
A19: Enterprise value | B19: =B16+B18 -> 2242.6019
A20: Equity value | B20: =B19-Assumptions!B12 -> 1892.6019
A21: Value per share | B21: =ROUND(B20/Assumptions!B13,2) -> 18.93
A22: NPV of free cash flow | B22: =NPV(WACC,C12:G12) -> 571.72309
A23: EV / EBITDA 2025 | B23: =B19/C5 -> 9.7082333
A24: Exit year | B24: =YEAR(Assumptions!B14)+5 -> 2029
