Workbook

Sheet Inputs
A1: Assumption | B1: 2025 | C1: 2026 | D1: 2027
A2: Revenue growth | B2: 0.08 | C2: 0.07 | D2: 0.06
A3: COGS % revenue | B3: 0.55 | C3: 0.54 | D3: 0.53
A5: Opex | B5: 120
A6: Depreciation rate | B6: 0.1
A7: Interest rate | B7: 0.06
A8: Tax rate | B8: 0.21
A9: DSO (days) | B9: 45
A10: Capex | B10: 60
A11: Debt repayment | B11: 25
A13: Year | B13: Opex growth
A14: 2025 | B14: 0.03
A15: 2026 | B15: 0.04
A16: 2027 | B16: 0.05

Sheet IS
A1: Income statement
A2: Year | B2: 2024 | C2: =B2+1 -> 2025 | D2: =C2+1 -> 2026 | E2: =D2+1 -> 2027
A3: Revenue | B3: 900 | C3: =B3*(1+INDEX(Inputs!$B$2:$D$2,MATCH(C$2,Inputs!$B$1:$D$1,0))) -> 972 | D3: =C3*(1+INDEX(Inputs!$B$2:$D$2,MATCH(D$2,Inputs!$B$1:$D$1,0))) -> 1040.04 | E3: =D3*(1+INDEX(Inputs!$B$2:$D$2,MATCH(E$2,Inputs!$B$1:$D$1,0))) -> 1102.4424
A4: COGS | C4: =C3*HLOOKUP(C$2,Inputs!$B$1:$D$3,3,FALSE()) -> 534.6 | D4: =D3*HLOOKUP(D$2,Inputs!$B$1:$D$3,3,FALSE()) -> 561.6216 | E4: =E3*HLOOKUP(E$2,Inputs!$B$1:$D$3,3,FALSE()) -> 584.29447
A5: Gross profit | C5: =C3-C4 -> 437.4 | D5: =D3-D4 -> 478.4184 | E5: =E3-E4 -> 518.14793
A6: Opex | C6: =Inputs!$B$5*(1+VLOOKUP(C$2,Inputs!A:B,2,FALSE())) -> 123.6 | D6: =C6*(1+VLOOKUP(D$2,Inputs!A:B,2,FALSE())) -> 128.544 | E6: =D6*(1+VLOOKUP(E$2,Inputs!A:B,2,FALSE())) -> 134.9712
A7: EBITDA | C7: =C5-C6 -> 313.8 | D7: =D5-D6 -> 349.8744 | E7: =E5-E6 -> 383.17673
A8: Depreciation | C8: =BS!B5*Inputs!$B$6 -> 40 | D8: =BS!C5*Inputs!$B$6 -> 42 | E8: =BS!D5*Inputs!$B$6 -> 43.8
A9: EBIT | C9: =C7-C8 -> 273.8 | D9: =D7-D8 -> 307.8744 | E9: =E7-E8 -> 339.37673
A10: Interest | C10: =BS!B7*Inputs!$B$7 -> 15 | D10: =BS!C7*Inputs!$B$7 -> 13.5 | E10: =BS!D7*Inputs!$B$7 -> 12
A11: Pre-tax income | C11: =C9-C10 -> 258.8 | D11: =D9-D10 -> 294.3744 | E11: =E9-E10 -> 327.37673
A12: Tax | C12: =MAX(0,C11*Inputs!$B$8) -> 54.348 | D12: =MAX(0,D11*Inputs!$B$8) -> 61.818624 | E12: =MAX(0,E11*Inputs!$B$8) -> 68.749113
A13: Net income | C13: =C11-C12 -> 204.452 | D13: =D11-D12 -> 232.55578 | E13: =E11-E12 -> 258.62762
A15: Average gross margin | B15: =SUMPRODUCT(C5:E5,1/C3:E3)/COUNT(C3:E3) -> 0.46
A16: Revenue over 1,000 | B16: =COUNTIF(C3:E3,">1000") -> 2
A17: Total revenue | B17: =SUMIF(C2:E2,">=2026",C3:E3) -> 2142.4824

Sheet BS
A1: Balance sheet
A2: Year | B2: 2024 | C2: =B2+1 -> 2025 | D2: =C2+1 -> 2026 | E2: =D2+1 -> 2027
A3: Cash | B3: 80 | C3: =B3+CF!C9 -> 229.61638 | D3: =C3+CF!D9 -> 410.78367 | E3: =D3+CF!E9 -> 620.51783
A4: Receivables | B4: 110 | C4: =IS!C3*Inputs!$B$9/365 -> 119.83562 | D4: =IS!D3*Inputs!$B$9/365 -> 128.22411 | E4: =IS!E3*Inputs!$B$9/365 -> 135.91756
A5: PP&E | B5: 400 | C5: =B5+Inputs!$B$10-IS!C8 -> 420 | D5: =C5+Inputs!$B$10-IS!D8 -> 438 | E5: =D5+Inputs!$B$10-IS!E8 -> 454.2
A6: Total assets | B6: =SUM(B3:B5) -> 590 | C6: =SUM(C3:C5) -> 769.452 | D6: =SUM(D3:D5) -> 977.00778 | E6: =SUM(E3:E5) -> 1210.6354
A7: Debt | B7: 250 | C7: =B7+CF!C8 -> 225 | D7: =C7+CF!D8 -> 200 | E7: =D7+CF!E8 -> 175
A8: Equity | B8: 340 | C8: =B8+IS!C13 -> 544.452 | D8: =C8+IS!D13 -> 777.00778 | E8: =D8+IS!E13 -> 1035.6354
A9: Total liabilities and equity | B9: =B7+B8 -> 590 | C9: =C7+C8 -> 769.452 | D9: =D7+D8 -> 977.00778 | E9: =E7+E8 -> 1210.6354
A10: Balance check | B10: =ROUND(B6-B9,6) -> 0 | C10: =ROUND(C6-C9,6) -> 0 | D10: =ROUND(D6-D9,6) -> 0 | E10: =ROUND(E6-E9,6) -> 0

Sheet CF
A1: Cash flow
A2: Year | B2: 2024 | C2: =B2+1 -> 2025 | D2: =C2+1 -> 2026 | E2: =D2+1 -> 2027
A3: Net income | C3: =IS!C13 -> 204.452 | D3: =IS!D13 -> 232.55578 | E3: =IS!E13 -> 258.62762
A4: Depreciation | C4: =IS!C8 -> 40 | D4: =IS!D8 -> 42 | E4: =IS!E8 -> 43.8
A5: Increase in receivables | C5: =BS!C4-BS!B4 -> 9.8356164 | D5: =BS!D4-BS!C4 -> 8.3884932 | E5: =BS!E4-BS!D4 -> 7.6934466
A6: Cash from operations | C6: =C3+C4-C5 -> 234.61638 | D6: =D3+D4-D5 -> 266.16728 | E6: =E3+E4-E5 -> 294.73417
A7: Capex | C7: =-Inputs!$B$10 -> -60 | D7: =-Inputs!$B$10 -> -60 | E7: =-Inputs!$B$10 -> -60
A8: Debt repaid | C8: =-MIN(Inputs!$B$11,BS!B7) -> -25 | D8: =-MIN(Inputs!$B$11,BS!C7) -> -25 | E8: =-MIN(Inputs!$B$11,BS!D7) -> -25
A9: Net change in cash | C9: =SUM(C6:C8) -> 149.61638 | D9: =SUM(D6:D8) -> 181.16728 | E9: =SUM(E6:E8) -> 209.73417
